03_finite_state_machines/03_01_detect_sequence_using_fsm.sv
//----------------------------------------------------------------------------
// Example
//----------------------------------------------------------------------------

module detect_4_bit_sequence_using_fsm
(
  input  clk,
  input  rst,
  input  a,
  output detected
);

  // Detection of the "1010" sequence

  // States (F — First, S — Second)
  enum logic[2:0]
  {
     IDLE = 3'b000,
     F1   = 3'b001,
     F0   = 3'b010,
     S1   = 3'b011,
     S0   = 3'b100
  }
  state, new_state;

  // State transition logic
  always_comb
  begin
    new_state = state;

    case (state)
      IDLE: if (  a) new_state = F1;
      F1:   if (~ a) new_state = F0;
      F0:   if (  a) new_state = S1;
            else     new_state = IDLE;
      S1:   if (~ a) new_state = S0;
            else     new_state = F1;
      S0:   if (  a) new_state = S1;
            else     new_state = IDLE;
    endcase
  end

  // Output logic (depends only on the current state)
  assign detected = (state == S0);

  // State update
  always_ff @ (posedge clk)
    if (rst)
      state <= IDLE;
    else
      state <= new_state;

endmodule

//----------------------------------------------------------------------------
// Task
//----------------------------------------------------------------------------

module detect_6_bit_sequence_using_fsm
(
  input  clk,
  input  rst,
  input  a,
  output detected
);

  // Task:
  // Implement a module that detects the "110011" input sequence
  //
  // Hint: See Lecture 3 for details

  typedef enum bit[2:0]{
    IDLE      = 3'd0,
    ST_1      = 3'd1,
    ST_11     = 3'd2,
    ST_110    = 3'd3,
    ST_1100   = 3'd4,
    ST_11001  = 3'd5,
    ST_110011 = 3'd6
  } state_e;

  state_e state, next_state;

  always_ff @(posedge clk)
    if(rst)
      state <= IDLE;
    else
      state <= next_state;

  always_comb begin
    next_state = state;
    case(state)
      IDLE: if(a) next_state = ST_1;
      ST_1: if(a) next_state = ST_11;
            else  next_state = IDLE;
      ST_11: if(~a) next_state = ST_110;
      ST_110: if(a) next_state = ST_1;
              else  next_state = ST_1100;
      ST_1100: if(a) next_state = ST_11001;
      	       else  next_state = IDLE;
      ST_11001: if(a) next_state = ST_110011;
      	        else  next_state = IDLE;
      ST_110011: if(a) next_state = ST_11;
      		 else  next_state = ST_110;
    endcase
  end
  assign detected = state == ST_110011;

endmodule

//----------------------------------------------------------------------------
// Testbench
//----------------------------------------------------------------------------

module testbench;

  logic clk;

  initial
  begin
    clk = '0;

    forever
      #500 clk = ~ clk;
  end

  logic rst;


  initial
  begin
    rst <= 'x;
    repeat (2) @ (posedge clk);
    rst <= '1;
    repeat (2) @ (posedge clk);
    rst <= '0;
  end

  logic a, det4bit, det6bit;
  detect_4_bit_sequence_using_fsm det4b (.detected (det4bit),  .*);
  detect_6_bit_sequence_using_fsm det6b (.detected (det6bit), .*);

  localparam n = 24;

  // The sequence of input values
  localparam [0 : n - 1] seq_a       = 24'b0011_0101_1001_1001_1010_1000;

  // The sequence of expected output values
  localparam [0 : n - 1] seq_det4bit = 24'b0000_0001_0000_0000_0000_1010;
  localparam [0 : n - 1] seq_det6bit = 24'b0000_0000_0000_0100_0100_0000;

  initial
  begin
    // Remove the comments below to generate the dump.vcd file and analyze it with GTKwave
    $dumpfile("dump_03_01.vcd");
    $dumpvars(0, testbench);

    @ (negedge rst);

    for (int i = 0; i < n; i ++)
    begin
      a <= seq_a [i];

      @ (posedge clk);

      $display ("%b %b (%b) %b (%b)",
        a,
        det4bit, seq_det4bit[i],
        det6bit, seq_det6bit[i]);

      if (   det4bit !== seq_det4bit[i]
          || det6bit !== seq_det6bit[i])
      begin
        $display ("%s FAIL - see log above", `__FILE__);
        $finish;
      end
    end

    $display ("%s PASS", `__FILE__);
    $finish;
  end

endmodule

03_finite_state_machines/dump_03_01.vcd
$date
	Sun Nov 19 11:21:01 2023
$end
$version
	Icarus Verilog
$end
$timescale
	1s
$end
$scope module testbench $end
$var wire 1 ! det6bit $end
$var wire 1 " det4bit $end
$var parameter 32 # n $end
$var parameter 24 $ seq_a $end
$var parameter 24 % seq_det4bit $end
$var parameter 24 & seq_det6bit $end
$var reg 1 ' a $end
$var reg 1 ( clk $end
$var reg 1 ) rst $end
$scope module det4b $end
$var wire 1 ' a $end
$var wire 1 ( clk $end
$var wire 1 ) rst $end
$var wire 1 " detected $end
$var reg 3 * new_state [2:0] $end
$var reg 3 + state [2:0] $end
$upscope $end
$scope module det6b $end
$var wire 1 ' a $end
$var wire 1 ( clk $end
$var wire 1 ) rst $end
$var wire 1 ! detected $end
$var reg 3 , next_state [2:0] $end
$var reg 3 - state [2:0] $end
$upscope $end
$scope begin $ivl_for_loop0 $end
$var integer 32 . i [31:0] $end
$upscope $end
$upscope $end
$enddefinitions $end
$comment Show the parameter values. $end
$dumpall
b10001000000 &
b10000000000001010 %
b1101011001100110101000 $
b11000 #
$end
#0
$dumpvars
b0 .
b0 -
b0 ,
bx +
bx *
x)
0(
x'
x"
0!
$end
#500
1(
#1000
0(
#1500
1)
1(
#2000
0(
#2500
b0 *
0"
b0 +
1(
#3000
0(
#3500
0'
0)
1(
#4000
0(
#4500
b1 .
1(
#5000
0(
#5500
b1 *
b1 ,
1'
b10 .
1(
#6000
0(
#6500
b10 ,
b1 +
b1 -
b11 .
1(
#7000
0(
#7500
b10 *
b11 ,
0'
b10 -
b100 .
1(
#8000
0(
#8500
b11 *
b1 ,
b10 +
b11 -
1'
b101 .
1(
#9000
0(
#9500
b0 ,
b100 *
0'
b1 -
b11 +
b110 .
1(
#10000
0(
#10500
b11 *
b1 ,
1"
b100 +
b0 -
1'
b111 .
1(
#11000
0(
#11500
b10 ,
b1 *
b1 -
0"
b11 +
b1000 .
1(
#12000
0(
#12500
b10 *
b11 ,
b1 +
b10 -
0'
b1001 .
1(
#13000
0(
#13500
b100 ,
b0 *
b11 -
b10 +
b1010 .
1(
#14000
0(
#14500
b1 *
b101 ,
b0 +
b100 -
1'
b1011 .
1(
#15000
0(
#15500
b110 ,
b101 -
b1 +
b1100 .
1(
#16000
0(
#16500
b10 *
b11 ,
1!
b110 -
0'
b1101 .
1(
#17000
0(
#17500
b100 ,
b0 *
0!
b11 -
b10 +
b1110 .
1(
#18000
0(
#18500
b1 *
b101 ,
b0 +
b100 -
1'
b1111 .
1(
#19000
0(
#19500
b110 ,
b101 -
b1 +
b10000 .
1(
#20000
0(
#20500
b10 *
b11 ,
1!
b110 -
0'
b10001 .
1(
#21000
0(
#21500
b1 ,
b11 *
1'
0!
b11 -
b10 +
b10010 .
1(
#22000
0(
#22500
b100 *
b0 ,
b11 +
b1 -
0'
b10011 .
1(
#23000
0(
#23500
b1 ,
b11 *
1'
b0 -
1"
b100 +
b10100 .
1(
#24000
0(
#24500
b100 *
b0 ,
0"
b11 +
b1 -
0'
b10101 .
1(
#25000
0(
#25500
b0 *
b0 -
1"
b100 +
b10110 .
1(
#26000
0(
#26500
0"
b0 +
b10111 .
1(
#27000
0(
#27500
b11000 .
1(
