04_arithmetics_and_pipelining/04_06_arithmetic_shift_or_signed_divide_by_power_of_2.sv
//----------------------------------------------------------------------------
// Example
//----------------------------------------------------------------------------

module arithmetic_right_shift_of_N_by_S_using_arithmetic_right_shift_operation
# (parameter N = 8, S = 3)
(input  [N - 1:0] a, output [N - 1:0] res);

  wire signed [N - 1:0] as = a;
  assign res = as >>> S;

endmodule

//----------------------------------------------------------------------------
// Task
//----------------------------------------------------------------------------

module arithmetic_right_shift_of_N_by_S_using_concatenation
# (parameter N = 8, S = 3)
(input  [N - 1:0] a, output [N - 1:0] res);

  // Task:
  //
  // Implement a module with the logic for the arithmetic right shift,
  // but without using ">>>" operation. You are allowed to use only
  // concatenations ({a, b}), bit repetitions ({ a { b }}), bit slices
  // and constant expressions.

  assign res = { {S + 1{a[N - 1]}}, a[N - 2:N - S - 2]};

endmodule

module arithmetic_right_shift_of_N_by_S_using_for_inside_always
# (parameter N = 8, S = 3)
(input  [N - 1:0] a, output logic [N - 1:0] res);

  // Task:
  //
  // Implement a module with the logic for the arithmetic right shift,
  // but without using ">>>" operation, concatenations or bit slices.
  // You are allowed to use only "always_comb" with a "for" loop
  // that iterates through the individual bits of the input.

  wire sign = a[N - 1];

  always_comb
    for(int i = 0; i < N; i ++)
      if (i > N - S - 1)
	res[i] = sign;
      else
	res[i] = a[i + S];

endmodule

module arithmetic_right_shift_of_N_by_S_using_for_inside_generate
# (parameter N = 8, S = 3)
(input  [N - 1:0] a, output [N - 1:0] res);

  // Task:
  // Implement a module that arithmetically shifts input exactly
  // by `S` bits to the right using "generate" and "for"
  genvar i;

  generate
    for (i = 0; i < N; i ++)
      if (i > N - S - 1)
	assign res[i] = a[N - 1];
      else if (i <= N - S - 1)
	assign res[i] = a[i + S];
  endgenerate

endmodule

//----------------------------------------------------------------------------
// Testbench
//----------------------------------------------------------------------------

module testbench;

  localparam N = 8, S = 3;

  logic signed [N - 1:0] a, res [0:3];

  arithmetic_right_shift_of_N_by_S_using_arithmetic_right_shift_operation
  # (.N (8), .S (3)) i4 (a, res [0]);

  arithmetic_right_shift_of_N_by_S_using_concatenation
  # (.N (8), .S (3)) i5 (a, res [1]);

  arithmetic_right_shift_of_N_by_S_using_for_inside_always
  # (.N (8), .S (3)) i6 (a, res [2]);

  arithmetic_right_shift_of_N_by_S_using_for_inside_generate
  # (.N (8), .S (3)) i7 (a, res [3]);

  initial
  begin
    $dumpfile("arith.vcd");
    $dumpvars(0, testbench);
    repeat (20)
    begin
      a = $urandom ();
      # 1

      $write ("TEST %d %b", a, a);

      for (int i = 0; i < 4; i ++)
        $write (" %d %b", res [i], res [i]);

      $display;

      for (int i = 1; i < 4; i ++)
        if (res [i] !== res [0])
        begin
          $display ("%s FAIL. EXPECTED %d %b",
            `__FILE__, res [0], res [0]);

          $finish;
        end

        /*
        if (res [i] !== a / 2 ** S)
        begin
          $display ("%s FAIL. EXPECTED %d %b",
            `__FILE__, a / (8'sd2 ** S), a / (8'sd2 ** S));

          $finish;
        end
        */
    end

    $display ("%s PASS", `__FILE__);
    $finish;
  end

endmodule

04_arithmetics_and_pipelining/arith.vcd
$date
	Sun Feb 25 15:29:48 2024
$end
$version
	Icarus Verilog
$end
$timescale
	1s
$end
$scope module testbench $end
$var parameter 32 ! N $end
$var parameter 32 " S $end
$var reg 8 # a [7:0] $end
$scope module i4 $end
$var wire 8 $ a [7:0] $end
$var wire 8 % as [7:0] $end
$var wire 8 & res [7:0] $end
$var parameter 32 ' N $end
$var parameter 32 ( S $end
$upscope $end
$scope module i5 $end
$var wire 8 ) a [7:0] $end
$var wire 8 * res [7:0] $end
$var parameter 32 + N $end
$var parameter 32 , S $end
$upscope $end
$scope module i6 $end
$var wire 8 - a [7:0] $end
$var wire 1 . sign $end
$var parameter 32 / N $end
$var parameter 32 0 S $end
$var reg 8 1 res [7:0] $end
$scope begin $ivl_for_loop0 $end
$var integer 32 2 i [31:0] $end
$upscope $end
$upscope $end
$scope module i7 $end
$var wire 8 3 a [7:0] $end
$var wire 8 4 res [7:0] $end
$var parameter 32 5 N $end
$var parameter 32 6 S $end
$scope begin genblk1[0] $end
$var parameter 2 7 i $end
$scope begin genblk1 $end
$upscope $end
$upscope $end
$scope begin genblk1[1] $end
$var parameter 2 8 i $end
$scope begin genblk1 $end
$upscope $end
$upscope $end
$scope begin genblk1[2] $end
$var parameter 3 9 i $end
$scope begin genblk1 $end
$upscope $end
$upscope $end
$scope begin genblk1[3] $end
$var parameter 3 : i $end
$scope begin genblk1 $end
$upscope $end
$upscope $end
$scope begin genblk1[4] $end
$var parameter 4 ; i $end
$scope begin genblk1 $end
$upscope $end
$upscope $end
$scope begin genblk1[5] $end
$var parameter 4 < i $end
$scope begin genblk1 $end
$upscope $end
$upscope $end
$scope begin genblk1[6] $end
$var parameter 4 = i $end
$scope begin genblk1 $end
$upscope $end
$upscope $end
$scope begin genblk1[7] $end
$var parameter 4 > i $end
$scope begin genblk1 $end
$upscope $end
$upscope $end
$upscope $end
$scope begin $ivl_for_loop1 $end
$var integer 32 ? i [31:0] $end
$upscope $end
$scope begin $ivl_for_loop2 $end
$var integer 32 @ i [31:0] $end
$upscope $end
$upscope $end
$enddefinitions $end
$comment Show the parameter values. $end
$dumpall
b111 >
b110 =
b101 <
b100 ;
b11 :
b10 9
b1 8
b0 7
b11 6
b1000 5
b11 0
b1000 /
b11 ,
b1000 +
b11 (
b1000 '
b11 "
b1000 !
$end
#0
$dumpvars
b0 @
b0 ?
b100 4
b100100 3
b1000 2
b100 1
0.
b100100 -
b100 *
b100100 )
b100 &
b100100 %
b100100 $
b100100 #
$end
#1
b11110000 &
b11110000 *
b11110000 1
b1000 2
1.
b11110000 4
b10000001 %
b10000001 #
b10000001 $
b10000001 )
b10000001 -
b10000001 3
b100 @
b100 ?
#2
b1 &
b1 *
b1 1
b1000 2
0.
b1 4
b1001 %
b1001 #
b1001 $
b1001 )
b1001 -
b1001 3
b100 @
b100 ?
#3
b1100 &
b1100 *
b1100 1
b1000 2
b1100 4
b1100011 %
b1100011 #
b1100011 $
b1100011 )
b1100011 -
b1100011 3
b100 @
b100 ?
#4
b1 &
b1 *
b1 1
b1000 2
b1 4
b1101 %
b1101 #
b1101 $
b1101 )
b1101 -
b1101 3
b100 @
b100 ?
#5
b11110001 &
b11110001 *
b11110001 1
b1000 2
1.
b11110001 4
b10001101 %
b10001101 #
b10001101 $
b10001101 )
b10001101 -
b10001101 3
b100 @
b100 ?
#6
b1100 &
b1100 *
b1100 1
b1000 2
0.
b1100 4
b1100101 %
b1100101 #
b1100101 $
b1100101 )
b1100101 -
b1100101 3
b100 @
b100 ?
#7
b10 &
b10 *
b10 1
b1000 2
b10 4
b10010 %
b10010 #
b10010 $
b10010 )
b10010 -
b10010 3
b100 @
b100 ?
#8
b0 &
b0 *
b0 1
b1000 2
b0 4
b1 %
b1 #
b1 $
b1 )
b1 -
b1 3
b100 @
b100 ?
#9
b1 &
b1 *
b1 1
b1000 2
b1 4
b1101 %
b1101 #
b1101 $
b1101 )
b1101 -
b1101 3
b100 @
b100 ?
#10
b1110 &
b1110 *
b1110 1
b1000 2
b1110 4
b1110110 %
b1110110 #
b1110110 $
b1110110 )
b1110110 -
b1110110 3
b100 @
b100 ?
#11
b111 &
b111 *
b111 1
b1000 2
b111 4
b111101 %
b111101 #
b111101 $
b111101 )
b111101 -
b111101 3
b100 @
b100 ?
#12
b11111101 &
b11111101 *
b11111101 1
b1000 2
1.
b11111101 4
b11101101 %
b11101101 #
b11101101 $
b11101101 )
b11101101 -
b11101101 3
b100 @
b100 ?
#13
b11110001 &
b11110001 *
b11110001 1
b1000 2
b11110001 4
b10001100 %
b10001100 #
b10001100 $
b10001100 )
b10001100 -
b10001100 3
b100 @
b100 ?
#14
b11111111 &
b11111111 *
b11111111 1
b1000 2
b11111111 4
b11111001 %
b11111001 #
b11111001 $
b11111001 )
b11111001 -
b11111001 3
b100 @
b100 ?
#15
b11111000 &
b11111000 *
b11111000 1
b1000 2
b11111000 4
b11000110 %
b11000110 #
b11000110 $
b11000110 )
b11000110 -
b11000110 3
b100 @
b100 ?
#16
b1000 2
b11000101 %
b11000101 #
b11000101 $
b11000101 )
b11000101 -
b11000101 3
b100 @
b100 ?
#17
b11110101 &
b11110101 *
b11110101 1
b1000 2
b11110101 4
b10101010 %
b10101010 #
b10101010 $
b10101010 )
b10101010 -
b10101010 3
b100 @
b100 ?
#18
b11111100 &
b11111100 *
b11111100 1
b1000 2
b11111100 4
b11100101 %
b11100101 #
b11100101 $
b11100101 )
b11100101 -
b11100101 3
b100 @
b100 ?
#19
b1110 &
b1110 *
b1110 1
b1000 2
0.
b1110 4
b1110111 %
b1110111 #
b1110111 $
b1110111 )
b1110111 -
b1110111 3
b100 @
b100 ?
#20
b100 @
b100 ?
